clickproj_rjd-0.1.0.dist-info/licenses/LICENSE
commands/__init__.py
commands/interactive_group.py
commands/cli/__init__.py
commands/cli/cli.py
commands/cli/greet/__init__.py
commands/cli/greet/greet.py
commands/cli/user/__init__.py
commands/cli/user/user.py
clickproj_rjd-0.1.0.dist-info/METADATA
clickproj_rjd-0.1.0.dist-info/WHEEL
clickproj_rjd-0.1.0.dist-info/entry_points.txt
clickproj_rjd-0.1.0.dist-info/top_level.txt
clickproj_rjd-0.1.0.dist-info/RECORD
