Metadata-Version: 2.4
Name: clickproj-rjd
Version: 0.1.0
Summary: A CLI application with interactive shell using Click
Author-email: Rajdeep Deb <rajdeep.dev98@gmail.com>
License: MIT
Project-URL: Homepage, https://github.com/rajdeepdev98/clickproj
Project-URL: Bug Tracker, https://github.com/rajdeepdev98/clickproj/issues
Project-URL: Documentation, https://github.com/rajdeepdev98/clickproj#readme
Keywords: cli,click,interactive,shell
Classifier: License :: OSI Approved :: MIT License
Classifier: Programming Language :: Python :: 3
Classifier: Programming Language :: Python :: 3.7
Classifier: Programming Language :: Python :: 3.8
Classifier: Programming Language :: Python :: 3.9
Classifier: Programming Language :: Python :: 3.10
Classifier: Programming Language :: Python :: 3.11
Classifier: Operating System :: OS Independent
Requires-Python: >=3.7
License-File: LICENSE
Requires-Dist: click>=8.0
Dynamic: license-file
